ninja_auth/__init__.py
ninja_auth/api.py
ninja_auth/schema.py
ninja_auth/tests.py
django_ninja_auth-0.1.7.dist-info/METADATA
django_ninja_auth-0.1.7.dist-info/WHEEL
django_ninja_auth-0.1.7.dist-info/RECORD
