Metadata-Version: 2.1
Name: django-ninja-auth
Version: 0.1.7
Summary: Django authorization views adapted to django-ninja
Home-page: https://github.com/mugartec/django-ninja-auth
License: WTFPL
Keywords: django,django-ninja,auth
Author: Martín Ugarte
Author-email: contact@martinugarte.com
Requires-Python: >=3.7,<4.0
Classifier: License :: Other/Proprietary License
Classifier: Programming Language :: Python :: 3
Classifier: Programming Language :: Python :: 3.7
Classifier: Programming Language :: Python :: 3.8
Classifier: Programming Language :: Python :: 3.9
Classifier: Programming Language :: Python :: 3.10
Classifier: Programming Language :: Python :: 3.11
Requires-Dist: django-ninja (>=0.22.2,<0.23.0)
Project-URL: Repository, https://github.com/mugartec/django-ninja-auth
